docs/conf.py
mulearn/__init__.py
mulearn/distributions.py
mulearn/fuzzifier.py
mulearn/kernel.py
mulearn/optimization.py
mulearn-1.1.3.dist-info/LICENSE
mulearn-1.1.3.dist-info/METADATA
mulearn-1.1.3.dist-info/WHEEL
mulearn-1.1.3.dist-info/top_level.txt
mulearn-1.1.3.dist-info/RECORD
