Metadata-Version: 2.1
Name: mulearn
Version: 1.1.3
Summary: A python package for inducing membership functions from labeled data
Author-email: Dario Malchiodi <dario.malchiodi@unimi.it>
License: Apache-2.0
Project-URL: Homepage, https://github.com/dariomalchiodi/mulearn
Project-URL: Documentation, https://mulearn.readthedocs.io/
Project-URL: Issues, https://github.com/dariomalchiodi/mulearn/issues
Keywords: fuzzy set,fuzzy membership,machine learning
Classifier: Programming Language :: Python :: 3
Classifier: Operating System :: OS Independent
Classifier: Development Status :: 4 - Beta
Requires-Python: >=3.8
License-File: LICENSE
Requires-Dist: gurobipy
Requires-Dist: json_fix
Requires-Dist: numpy<2.0
Requires-Dist: tqdm
Requires-Dist: scipy
Requires-Dist: scikit-learn
Requires-Dist: tensorflow==2.17
